{
  "fluentMethods": true,
  "clientRootFolder": "microserviziapp",
  "relationships": [],
  "fields": [
    {
      "fieldName": "username",
      "fieldType": "String",
      "fieldValidateRules": ["required"]
    },
    {
      "fieldName": "password",
      "fieldType": "String",
      "fieldValidateRules": ["required"]
    },
    {
      "fieldName": "usertype",
      "fieldType": "Integer"
    }
  ],
  "changelogDate": "20200526133236",
  "dto": "mapstruct",
  "searchEngine": false,
  "service": "serviceImpl",
  "entityTableName": "utente",
  "databaseType": "sql",
  "readOnly": false,
  "jpaMetamodelFiltering": false,
  "pagination": "pagination",
  "microserviceName": "microserviziapp"
}
